COPYING
MANIFEST.in
README.rst
setup.py
PyOBEX/__init__.py
PyOBEX/client.py
PyOBEX/common.py
PyOBEX/headers.py
PyOBEX/requests.py
PyOBEX/responses.py
PyOBEX/server.py
PyOBEX.egg-info/PKG-INFO
PyOBEX.egg-info/SOURCES.txt
PyOBEX.egg-info/dependency_links.txt
PyOBEX.egg-info/requires.txt
PyOBEX.egg-info/top_level.txt
examples/fileserver.py
examples/get_files.py
examples/pbapclient.py
examples/pushclient.py
examples/pushserver.py
examples/threaded_connection.py