Metadata-Version: 2.1
Name: PyOBEX
Version: 0.31
Summary: A package implementing aspects of the Object Exchange (OBEX) protocol.
Home-page: https://gitlab.com/dboddie/pyobex
Author: David Boddie
Author-email: david@boddie.org.uk
License: GPL version 3 (or later)
Project-URL: Bug Reports, https://gitlab.com/dboddie/pyobex/-/issues
Project-URL: Source, https://gitlab.com/dboddie/pyobex
Platform: Cross-platform
License-File: COPYING
